{
	"type": "FeatureCollection",
	"crs": {
		"type": "name",
		"properties": {
			"name": "urn:ogc:def:crs:OGC:1.3:CRS84"
		}
	},

	"features": [

		{
			"type": "Feature",
			"properties": {
				"value": 0.000000,
				"aleatorio": 3050.000000
			},
			"geometry": {
				"type": "Point",
				"coordinates": [-52.32156543499039, -21.163776874013813]
			}
		},
		{
			"type": "Feature",
			"properties": {
				"value": 0.000000,
				"aleatorio": 30494.000000
			},
			"geometry": {
				"type": "Point",
				"coordinates": [-54.17772601667923, -23.386212462676738]
			}
		}
	]
}