{
	"type": "FeatureCollection",
	"crs": {
		"type": "name",
		"properties": {
			"name": "urn:ogc:def:crs:OGC:1.3:CRS84"
		}
	},
	"features": [{
		"type": "Feature",
		"properties": {
			"value": 0.000000,
			"aleatorio": 29069.000000
		},
		"geometry": {
			"type": "Point",
			"coordinates": [-59.82586821661134, 2.158481925333142]
		}
	}, {
			"type": "Feature",
			"properties": {
				"value": 0.000000,
				"aleatorio": 10070.000000
			},
			"geometry": {
				"type": "Point",
				"coordinates": [-68.159149912401389, 0.859735725554899]
			}
		},{
			"type": "Feature",
			"properties": {
				"value": 0.000000,
				"aleatorio": 41383.000000
			},
			"geometry": {
				"type": "Point",
				"coordinates": [-72.878292545705065, -9.021543620678148]
			}
		}, {
			"type": "Feature",
			"properties": {
				"value": 1.000000,
				"aleatorio": 49322.000000
			},
			"geometry": {
				"type": "Point",
				"coordinates": [-51.238196988490955, -9.788110464178892]
			}
		},{
			"type": "Feature",
			"properties": {
				"value": 1.000000,
				"aleatorio": 40580.000000
			},
			"geometry": {
				"type": "Point",
				"coordinates": [-51.225057491952043, -20.095735549780485]
			}
		}
 ]
}