{
"type": "FeatureCollection",
"crs": { "type": "name", "properties": { "name": "urn:ogc:def:crs:OGC:1.3:CRS84" } },
                                                                                
"features": [
{ "type": "Feature", "properties": { "Id": 0, "Classe_Uso": "Vegetacao Remanescente" }, "geometry": { "type": "Point", "coordinates": [ -49.435, -16.960 ] } }
]
}
